verifiably_checker/__init__.py
verifiably_checker/attestation.py
verifiably_checker/root.pem
verifiably_checker-0.0.3.dist-info/LICENSE
verifiably_checker-0.0.3.dist-info/METADATA
verifiably_checker-0.0.3.dist-info/WHEEL
verifiably_checker-0.0.3.dist-info/top_level.txt
verifiably_checker-0.0.3.dist-info/RECORD
